geodata/AlternateNames.py
geodata/ArgumentParserNoExit.py
geodata/CachedDictionary.py
geodata/Country.py
geodata/DB.py
geodata/Example.py
geodata/Features.py
geodata/FileReader.py
geodata/GeoDB.py
geodata/GeoSearch.py
geodata/GeoUtil.py
geodata/Geodata.py
geodata/GeodataBuild.py
geodata/GeodataFiles.py
geodata/LoadAlternateNames.py
geodata/Loc.py
geodata/MatchScore.py
geodata/Normalize.py
geodata/Optimize.py
geodata/QueryList.py
geodata/Test.py
geodata/__init__.py
geodata/__version__.py
geodata-1.7.1.dist-info/LICENSE
geodata-1.7.1.dist-info/METADATA
geodata-1.7.1.dist-info/WHEEL
geodata-1.7.1.dist-info/top_level.txt
geodata-1.7.1.dist-info/RECORD
