Metadata-Version: 2.1
Name: geodata
Version: 1.7.1
Summary: Provide a place lookup gazeteer based on files from geonames.org
Home-page: https://github.com/corb555/Geodata
Author: Mike Herbert
Author-email: corb@aol.com
License: MIT
Platform: UNKNOWN
Classifier: Programming Language :: Python :: 3.6
Classifier: License :: OSI Approved :: GNU General Public License v2 (GPLv2)
Classifier: Operating System :: OS Independent
Classifier: Development Status :: 4 - Beta
Classifier: Intended Audience :: Developers
Classifier: Natural Language :: English
Classifier: Topic :: Scientific/Engineering :: GIS
Requires-Dist: unidecode
Requires-Dist: phonetics
Requires-Dist: rapidfuzz
